NotebookRender/__init__.py
NotebookRender/custom_exception.py
NotebookRender/logger.py
NotebookRender/youtube.py
notebookrender-0.0.2.dist-info/LICENSE
notebookrender-0.0.2.dist-info/METADATA
notebookrender-0.0.2.dist-info/WHEEL
notebookrender-0.0.2.dist-info/top_level.txt
notebookrender-0.0.2.dist-info/RECORD
